[
  {
    "Id": 1,
    "Mitgliedsname": "Jon Snow",
    "Haus": "Stark",
    "Ereignis": "Sieg in der Schlacht der Bastarde",
    "Datum": "2016-06-26"
  },
  {
    "Id": 2,
    "Mitgliedsname": "Cersei Lannister",
    "Haus": "Lannister",
    "Ereignis": "Krönung zur Königin",
    "Datum": "2016-12-11"
  },
  {
    "Id": 3,
    "Mitgliedsname": "Daenerys Targaryen",
    "Haus": "Targaryen",
    "Ereignis": "Eroberung von Drachenstein",
    "Datum": "2017-04-17"
  },
  {
    "Id": 4,
    "Mitgliedsname": "Robb Stark",
    "Haus": "Stark",
    "Ereignis": "Krönung zum König des Nordens",
    "Datum": "2011-09-01"
  },
  {
    "Id": 5,
    "Mitgliedsname": "Tyrion Lannister",
    "Haus": "Lannister",
    "Ereignis": "Verurteilung durch den Vater",
    "Datum": "2014-05-15"
  },
  {
    "Id": 6,
    "Mitgliedsname": "Jaime Lannister",
    "Haus": "Lannister",
    "Ereignis": "Flucht aus Riverrun",
    "Datum": "2015-04-12"
  },
  {
    "Id": 7,
    "Mitgliedsname": "Sansa Stark",
    "Haus": "Stark",
    "Ereignis": "Flucht von den Bolton",
    "Datum": "2016-05-23"
  },
  {
    "Id": 8,
    "Mitgliedsname": "Bran Stark",
    "Haus": "Stark",
    "Ereignis": "Erster Kontakt mit dem Dreiäugigen Raben",
    "Datum": "2013-11-17"
  },
  {
    "Id": 9,
    "Mitgliedsname": "Jorah Mormont",
    "Haus": "Targaryen",
    "Ereignis": "Flucht nach Essos",
    "Datum": "2014-08-21"
  },
  {
    "Id": 10,
    "Mitgliedsname": "Stannis Baratheon",
    "Haus": "Baratheon",
    "Ereignis": "Verlust von Winterfell",
    "Datum": "2015-06-21"
  },
  {
    "Id": 11,
    "Mitgliedsname": "Viserys Targaryen",
    "Haus": "Targaryen",
    "Ereignis": "Eroberung von Essos",
    "Datum": "2011-05-02"
  },
  {
    "Id": 12,
    "Mitgliedsname": "Sandor Clegane",
    "Haus": "Greyjoy",
    "Ereignis": "Vergeltung für die Bruderschaft ohne Banner",
    "Datum": "2015-07-06"
  },
  {
    "Id": 13,
    "Mitgliedsname": "Robb Stark",
    "Haus": "Stark",
    "Ereignis": "Heirat mit Talisa Maegyr",
    "Datum": "2013-03-03"
  },
  {
    "Id": 14,
    "Mitgliedsname": "Daenerys Targaryen",
    "Haus": "Targaryen",
    "Ereignis": "Der erste Drachenflug",
    "Datum": "2016-03-14"
  },
  {
    "Id": 15,
    "Mitgliedsname": "Hodor",
    "Haus": "Stark",
    "Ereignis": "Tod von Hodor",
    "Datum": "2016-05-25"
  },
  {
    "Id": 16,
    "Mitgliedsname": "Brienne von Tarth",
    "Haus": "Stark",
    "Ereignis": "Schlacht von Blackwater",
    "Datum": "2012-05-28"
  },
  {
    "Id": 17,
    "Mitgliedsname": "Theon Greyjoy",
    "Haus": "Greyjoy",
    "Ereignis": "Übernahme von Winterfell",
    "Datum": "2013-10-14"
  },
  {
    "Id": 18,
    "Mitgliedsname": "Ramsay Bolton",
    "Haus": "Stark",
    "Ereignis": "Ermordung von Rickon Stark",
    "Datum": "2016-04-10"
  },
  {
    "Id": 19,
    "Mitgliedsname": "Benjen Stark",
    "Haus": "Stark",
    "Ereignis": "Rückkehr von den Toten",
    "Datum": "2016-05-09"
  },
  {
    "Id": 20,
    "Mitgliedsname": "Tormund Giantsbane",
    "Haus": "Stark",
    "Ereignis": "Besuch von Eastwatch",
    "Datum": "2017-08-20"
  },
  {
    "Id": 21,
    "Mitgliedsname": "Arya Stark",
    "Haus": "Stark",
    "Ereignis": "Erster Mord (Meryn Trant)",
    "Datum": "2015-04-14"
  },
  {
    "Id": 22,
    "Mitgliedsname": "Varys",
    "Haus": "Targaryen",
    "Ereignis": "Verschwörung gegen die Lannisters",
    "Datum": "2013-06-07"
  },
  {
    "Id": 23,
    "Mitgliedsname": "Bran Stark",
    "Haus": "Stark",
    "Ereignis": "Der Beginn der Reise als Dreiäugiger Rabe",
    "Datum": "2016-04-03"
  },
  {
    "Id": 24,
    "Mitgliedsname": "Podrick Payne",
    "Haus": "Lannister",
    "Ereignis": "Überleben der Schlacht von Blackwater",
    "Datum": "2012-05-28"
  },
  {
    "Id": 25,
    "Mitgliedsname": "Cersei Lannister",
    "Haus": "Lannister",
    "Ereignis": "Zerstörung des Tempels von Baelor",
    "Datum": "2016-05-27"
  },
  {
    "Id": 26,
    "Mitgliedsname": "Daenerys Targaryen",
    "Haus": "Targaryen",
    "Ereignis": "Zerstörung der Sklavenmärkte in Meereen",
    "Datum": "2015-07-12"
  },
  {
    "Id": 27,
    "Mitgliedsname": "Jon Snow",
    "Haus": "Stark",
    "Ereignis": "Rückkehr von den Toten",
    "Datum": "2016-04-01"
  },
  {
    "Id": 28,
    "Mitgliedsname": "Brienne von Tarth",
    "Haus": "Stark",
    "Ereignis": "Sieg in der Schlacht von Winterfell",
    "Datum": "2016-06-26"
  },
  {
    "Id": 29,
    "Mitgliedsname": "Arya Stark",
    "Haus": "Stark",
    "Ereignis": "Die Rückkehr nach Winterfell",
    "Datum": "2017-07-21"
  },
  {
    "Id": 30,
    "Mitgliedsname": "Jaime Lannister",
    "Haus": "Lannister",
    "Ereignis": "Verlust von der rechten Hand",
    "Datum": "2013-11-03"
  }
]